arulesviz/__init__.py
arulesviz/arulesviz.py
arulesviz-0.0.2.dist-info/LICENSE
arulesviz-0.0.2.dist-info/METADATA
arulesviz-0.0.2.dist-info/WHEEL
arulesviz-0.0.2.dist-info/top_level.txt
arulesviz-0.0.2.dist-info/RECORD
