Metadata-Version: 2.1
Name: arulesviz
Version: 0.0.2
Summary: Association Rules visualisation tool
Home-page: https://github.com/zveryansky/python-arulesviz
Author: Alex Zverianskii
Author-email: 
License: MIT
Keywords: association rules graph bqplot arules arulesviz apriori lift slift
Platform: UNKNOWN
Classifier: License :: OSI Approved :: MIT License
Classifier: Programming Language :: Python :: 3.6
Classifier: Programming Language :: Python :: 3.7
Requires-Dist: ipywidgets
Requires-Dist: bqplot
Requires-Dist: efficient-apriori
